{
	"textures": {
        "particle": "cakeisalie:block/chocolate_roll_side",
		"bothside": "cakeisalie:block/chocolate_roll_bothside",
		"side": "cakeisalie:block/chocolate_roll_side",
        "top": "cakeisalie:block/chocolate_roll_top"
    },
	 "elements": [
        {
				"from": [ 1, 0, 4 ],
		  		"to": [ 15, 7, 12 ],
            "faces": {
					"down": { "texture": "#top", "cullface": "down" },
					"north": { "texture": "#bothside" },
					"south": { "texture": "#bothside" },
					"east": { "texture": "#side" },
					"west": { "texture": "#side" },
					"up": { "texture": "#top" }
            }
        }
	]
}
